caraml/__init__.py
caraml/upi/__init__.py
caraml/upi/utils.py
caraml/upi/version.py
caraml/upi/v1/__init__.py
caraml/upi/v1/header_pb2.py
caraml/upi/v1/header_pb2.pyi
caraml/upi/v1/header_pb2_grpc.py
caraml/upi/v1/header_pb2_grpc.pyi
caraml/upi/v1/observation_log_pb2.py
caraml/upi/v1/observation_log_pb2.pyi
caraml/upi/v1/observation_log_pb2_grpc.py
caraml/upi/v1/observation_log_pb2_grpc.pyi
caraml/upi/v1/prediction_log_pb2.py
caraml/upi/v1/prediction_log_pb2.pyi
caraml/upi/v1/prediction_log_pb2_grpc.py
caraml/upi/v1/prediction_log_pb2_grpc.pyi
caraml/upi/v1/router_log_pb2.py
caraml/upi/v1/router_log_pb2.pyi
caraml/upi/v1/router_log_pb2_grpc.py
caraml/upi/v1/router_log_pb2_grpc.pyi
caraml/upi/v1/table_pb2.py
caraml/upi/v1/table_pb2.pyi
caraml/upi/v1/table_pb2_grpc.py
caraml/upi/v1/table_pb2_grpc.pyi
caraml/upi/v1/type_pb2.py
caraml/upi/v1/type_pb2.pyi
caraml/upi/v1/type_pb2_grpc.py
caraml/upi/v1/type_pb2_grpc.pyi
caraml/upi/v1/upi_pb2.py
caraml/upi/v1/upi_pb2.pyi
caraml/upi/v1/upi_pb2_grpc.py
caraml/upi/v1/upi_pb2_grpc.pyi
caraml/upi/v1/variable_pb2.py
caraml/upi/v1/variable_pb2.pyi
caraml/upi/v1/variable_pb2_grpc.py
caraml/upi/v1/variable_pb2_grpc.pyi
caraml_upi_protos-1.0.0.dist-info/LICENSE
caraml_upi_protos-1.0.0.dist-info/METADATA
caraml_upi_protos-1.0.0.dist-info/WHEEL
caraml_upi_protos-1.0.0.dist-info/top_level.txt
caraml_upi_protos-1.0.0.dist-info/RECORD
