Metadata-Version: 2.1
Name: caraml-upi-protos
Version: 1.0.0
Summary: Generated Python code from caraml-dev/universal-prediction-interface
Home-page: UNKNOWN
Author: CaraML Developer
Author-email: dsp@gojek.com
License: UNKNOWN
Keywords: caraml,upi,grpc,protobuf,stub
Platform: UNKNOWN
Requires-Python: >=3.7
Requires-Dist: grpcio-tools >=1.21.1
Requires-Dist: googleapis-common-protos >=1.50.0
Provides-Extra: test
Requires-Dist: pytest ==7.1.2 ; extra == 'test'
Requires-Dist: pytest-benchmark ==3.4.1 ; extra == 'test'
Requires-Dist: pandas ; extra == 'test'
